LICENSE.txt
MANIFEST.in
README.rst
setup.cfg
setup.py
api/__init__.py
api/admin.py
api/apps.py
api/comparing.py
api/models.py
api/serializers.py
api/tests.py
api/urls.py
api/views.py
api/migrations/0001_initial.py
api/migrations/0002_task_created_by.py
api/migrations/0003_task_status.py
api/migrations/0004_alter_task_status.py
api/migrations/0005_tag_tagtaskmapping.py
api/migrations/0006_tag_status.py
api/migrations/__init__.py
dj_todo.egg-info/PKG-INFO
dj_todo.egg-info/SOURCES.txt
dj_todo.egg-info/dependency_links.txt
dj_todo.egg-info/top_level.txt